{
  "title1": "Hỗ trợ",
  "content": [
    "Chính sách trả hàng",
    "Điều khoản dịch vụ",
    "Điều khoản dịch vụ mua bán UTO",
    "Danh mục yêu cầu hồ sơ pháp lý Nhà bán & Hàng hóa",
    "Chính sách vận chuyển"
  ],
  "title2": "Chúng tôi trên mạng xã hội",
  "logo": [
    {
      "img": "facebook icon.png",
      "path": "https://www.facebook.com/uto.vn"
    },
    {
      "img": "youtube icon.png",
      "path": "https://www.youtube.com/channel/UCVm2Adt_uRIUELiqs_lDscg"
    },
    {
      "img": "zalo icon.png",
      "path": "https://zalo.me/3390877102212137867"
    },
    {
      "img": "tiktok icon.png",
      "path": "https://www.tiktok.com/@uniontek_official"
    }
  ],
  "downloadImg": ["google play.png", "app store.png"],
  "support": {
    "img": "support icon.png",
    "title": "Tổng đài hỗ trợ 24/7",
    "phone": "1900 88 66 33"
  },
  "description": "Đăng ký để cập nhật thton tin mới nhất về các chương trình khuyến mãi và nhận được voucher hấp dẫn",
  "copyright": "© 2022 UTO",
  "slogan": "Nâng tầm thương hiệu của bạn"
}
